dreader/__init__.py
dreader/config_params/__init__.py
dreader/config_params/params.py
dreader/meta.py
dreader/py.typed
dreader/summary/__init__.py
dreader/summary/csv_read.py
dreader/summary/summary_stats.py
dreader-0.0.4.dist-info/WHEEL
dreader-0.0.4.dist-info/METADATA
dreader-0.0.4.dist-info/RECORD
