Metadata-Version: 2.1
Name: dreader
Version: 0.0.4
Summary: Deepdog Reader
License: GPL-3.0-only
Author: Deepak
Author-email: dmallubhotla+github@gmail.com
Requires-Python: >=3.7
Classifier: License :: OSI Approved :: GNU General Public License v3 (GPLv3)
Classifier: Programming Language :: Python :: 3
Classifier: Programming Language :: Python :: 3.10
Classifier: Programming Language :: Python :: 3.7
Classifier: Programming Language :: Python :: 3.8
Classifier: Programming Language :: Python :: 3.9
